w3/__init__.py
w3/core/__init__.py
w3/core/async_mixin.py
w3/core/client/__init__.py
w3/core/client/client.py
w3/core/contract/__init__.py
w3/core/contract/contracts.py
w3/core/gas_strategy/__init__.py
w3/core/gas_strategy/eip1559_gas_strategy.py
w3/core/gas_strategy/gas_strategy.py
w3/core/gas_strategy/old_gas_strategy.py
w3/core/network/__init__.py
w3/core/network/network.py
w3/core/token_amount/__init__.py
w3/core/token_amount/token_amount.py
w3/core/transaction/__init__.py
w3/core/transaction/transactions.py
w3/core/w3/__init__.py
w3/core/w3/w3.py
w3/core/wallet/__init__.py
w3/core/wallet/wallet.py
w3/utils/__init__.py
w3/utils/exceptions.py
w3/utils/regex.py
w3/utils/types.py
w3/utils/utils.py
w3_wrapper-0.4.dist-info/METADATA
w3_wrapper-0.4.dist-info/WHEEL
w3_wrapper-0.4.dist-info/top_level.txt
w3_wrapper-0.4.dist-info/RECORD
