Metadata-Version: 2.1
Name: w3-wrapper
Version: 0.4
Summary: an object-oriented wrapper over the web3py library
Home-page: 
Author: ilyx
Author-email: felinooper@gmail.com
Classifier: Programming Language :: Python :: 3
Classifier: License :: OSI Approved :: MIT License
Classifier: Operating System :: OS Independent
Requires-Python: >=3.11
Requires-Dist: web3
Requires-Dist: asyncio
Requires-Dist: hexbytes
Requires-Dist: pydantic
